{
  "00000E52": {
    "Record Header": [
      "SPEL",
      "131",
      "",
      "{Skyrim.esm:000E52}",
      "00 00 00 00",
      "44",
      "00 00"
    ],
    "EDID - Editor ID": "AbMG08AncanoMagicka",
    "OBND - Object Bounds": [
      "0",
      "0",
      "0",
      "0",
      "0",
      "0"
    ],
    "ETYP - Equipment Type": "{Skyrim.esm:013F44}",
    "DESC - Description": "",
    "SPIT - Data": [
      "792",
      "",
      "Spell",
      "0.500000",
      "Constant Effect",
      "Self",
      "0.000000",
      "0.000000",
      "{Null:000000}"
    ],
    "Effects": [
      [
        "{Skyrim.esm:05312B}",
        [
          "100.000000",
          "0",
          "0"
        ]
      ]
    ]
  }
}